{
    "acolyte" : {
        "description" : "generic description for Acolyte",
        "skillProfs" : ["Insight", "Religion"],
        "languages" : "Two of your choice",
        "equipment" : ["A holy symbol", 
                    "A prayer book or prayer wheel", 
                    "5 sticks of incense",
                    "Vestments",
                    "A set of common clothes",
                    "A belt pouch containing 15 gp"]
    },
    "charlatan" : {
        "description" : "generic description for charlatan",
        "skillProfs" : ["Deception", "Sleight of Hand"],
        "toolProfs" : ["Disguise kit", "Forgery Kit"],
        "equipment" : ["A set of fine clothes",
                      "A disguise kit",
                      "Tools of the con of your choice (ten stoppered bottles filled with coloured liquid, a set of weighted dice, a deck of marked cards, or a signet ring of an imaginary duke)",
                      "A belt pouch containing 15 gp"]
    },
    
    "criminal" : {
        "description" : "generic description for criminal",
        "skillProfs" : ["Deception", "Stealth"],
        "toolProfs" : ["One type of gaming set", 
                      "Thieves' tools"],
        "equipment" : ["A crowbar", 
                    "A set of dark common clothes including a hood",
                    "A belt pouch containing 15 gp"]
    },
    "entertainer" : {
        "description" : "generic description for entertainer",
        "skillProfs" : ["Acrobatics", "Performance"],
        "toolProfs" : ["Disguise Kit", 
                      "One type of musical instrument"],
        "equipment" : ["A musical instrument (one of your choice)", 
                    "The favour of an admirer (love letter, lock of hair, or trinket)", 
                    "A costume",
                    "A belt pouch containing 15 gp"]
    },
    "folkHero" : {
        "description" : "generic description for folk hero",
        "skillProfs" : ["Animal Handling", "Survival"],
        "toolProfs" : ["One type of artisan's tools","Land vehicles"],
        "equipment" : ["A set of artisan's tools (one of your choice)", 
                    "A shoval", 
                    "An iron pot",
                    "A set of common clothes",
                    "A belt pouch containing 15 gp"]
    },
    "guildArtisan" : {
        "description" : "generic description for guild artisan",
        "skillProfs" : ["Insight", "Persuasion"],
        "toolProfs" : ["One type of artisan's tools"],
        "equipment" : ["A set of artisan's tools (one of your choice)", 
                    "A letter of introduction from your guild",
                    "A set of traveler's clothes",
                    "A belt pouch containing 15 gp"]
    },
    "hermit" : {
        "description" : "generic description for hermit",
        "skillProfs" : ["Medicine", "Religion"],
        "toolProfs" : ["Herbalism Kit"],
        "languages" : "One of your choice",
        "equipment" : ["A scroll case stuffed full of notes from your studies or prayers", 
                    "A winter blanket", 
                    "An herbalism kit",
                    "A set of common clothes",
                    "A belt pouch containing 5 gp"]
    },
    "noble" : {
        "description" : "generic description for noble",
        "skillProfs" : ["History", "Persuasion"],
        "languages" : "One of your choice",
        "toolProfs" : ["One type of gaming set"],
        "equipment" : ["A scroll of pedigree",
                    "A signet ring",
                    "A set of fine clothes",
                    "A purse containing 25 gp"]
    },
    "outlander" : {
        "description" : "generic description for outlander",
        "skillProfs" : ["Athletics", "Survival"],
        "languages" : "One of your choice",
        "toolProfs" : ["One type of musical instrument"],
        "equipment" : ["A staff", 
                    "A hunting trap", 
                    "A trophy from an animal you killed",
                    "A set of traveler's clothes",
                    "A belt pouch containing 10 gp"]
    },
    "sage" : {
        "description" : "generic description for sage",
        "skillProfs" : ["Arcana", "History"],
        "languages" : "Two of your choice",
        "equipment" : ["A bottle of black ink", 
                    "A quill", 
                    "A small knife",
                    "A letter from a dead colleague posing a question you have not yet been able to answer",
                    "A set of common clothes",
                    "A belt pouch containing 10 gp"]
    },
    "sailor" : {
        "description" : "generic description for Acolyte",
        "skillProfs" : ["Athletics", "Perception"],
        "toolProfs" : ["Navigator's tools", "Water vehicles"],
        "equipment" : ["A belaying pin (club)", 
                    "A lucky charm such as a rabbit foot or a small stone with a hole in the center",
                    "A set of common clothes",
                    "A belt pouch containing 10 gp"]
    },
    "soldier" : {
        "description" : "generic description for soldier",
        "skillProfs" : ["Athletics", "Intimidation"],
        "toolProfs" : ["One type of gaming set",
                       "Land vehicles"],
        "equipment" : ["An insignia of rank", 
                    "A trophy taken from a fallen enemy (a dagger, broken blade, or a piece of a banner)", 
                    "A set of bone dice or deck of cards",
                    "A set of common clothes",
                    "A belt pouch containing 10 gp"]
    },
    "urchin" : {
        "description" : "generic description for urchin",
        "skillProfs" : ["Sleight of Hand", "Stealth"],
        "toolProfs" : ["Disguise Kit", "Thieves' tools"],
        "equipment" : ["A small knife", 
                    "A map of the city you grew up in", 
                    "A pet mouse",
                    "A token to remember your parents by",
                    "A set of common clothes",
                    "A belt pouch containing 10 gp"]
    }
}